src/tradingBot/__init__.py
src/tradingBot/backtest/option/butterfly.py
src/tradingBot/backtest/option/credit_iron_condor.py
src/tradingBot/backtest/option/single_option.py
src/tradingBot/backtest/option/spread.py
src/tradingBot/backtest/option/strategy.py
src/tradingBot/backtest/stock/bollingerBands.py
src/tradingBot/backtest/stock/macd.py
src/tradingBot/backtest/stock/mfi.py
src/tradingBot/backtest/stock/rsi.py
src/tradingBot/consts/RGB.py
src/tradingBot/consts/asset.py
src/tradingBot/consts/strategy.py
src/tradingBot/excel/accountBook.py
src/tradingBot/excel/acctPositionSheet.py
src/tradingBot/excel/backtestBook.py
src/tradingBot/excel/backtestSheet.py
src/tradingBot/excel/dataSheet.py
src/tradingBot/excel/fundamentalSheet.py
src/tradingBot/excel/mlbook.py
src/tradingBot/excel/mlsheet.py
src/tradingBot/excel/positionBook.py
src/tradingBot/excel/positionSheet.py
src/tradingBot/excel/transactionSheet.py
src/tradingBot/excel/watchListBook.py
src/tradingBot/optionPosition/butterfly.py
src/tradingBot/optionPosition/core.py
src/tradingBot/optionPosition/iron_condor.py
src/tradingBot/optionPosition/single_leg.py
src/tradingBot/optionPosition/spread.py
src/tradingBot/settings/env.py
src/tradingBot/settings/tradeConfig.py
src/tradingBot/shell/analyzer.py
src/tradingBot/shell/backtester.py
src/tradingBot/shell/watchlist_refresher.py
src/tradingBot/utils/calcProb.py
src/tradingBot/utils/dataGetter.py
src/tradingBot/utils/optionTool.py
trading_robot-0.0.1.dist-info/METADATA
trading_robot-0.0.1.dist-info/WHEEL
trading_robot-0.0.1.dist-info/licenses/LICENSE
trading_robot-0.0.1.dist-info/RECORD
