Metadata-Version: 2.1
Name: trading-robot
Version: 0.0.1
Summary: Option Trading Robot package
Project-URL: Homepage, https://github.com/pypa/tradingBotproject
Project-URL: Bug Tracker, https://github.com/pypa/tradingBot/issues
Author-email: Jim Huang <jim.huang.taipei@outlook.com>
License-File: LICENSE
Classifier: License :: OSI Approved :: MIT License
Classifier: Operating System :: OS Independent
Classifier: Programming Language :: Python :: 3
Requires-Python: >=3.7
